mybase_lucien/__init__.py
mybase_lucien/myip.py
mybase_lucien/mylocale.py
mybase_lucien/myselenium.py
mybase_lucien-2.1.2.dist-info/LICENSE
mybase_lucien-2.1.2.dist-info/METADATA
mybase_lucien-2.1.2.dist-info/WHEEL
mybase_lucien-2.1.2.dist-info/top_level.txt
mybase_lucien-2.1.2.dist-info/RECORD
