Metadata-Version: 2.1
Name: mybase-lucien
Version: 2.1.2
Summary: This package is used for setting up base locales.
Home-page: https://github.com/lucienshawls/mybase-lucien
Author: Lucien
Author-email: myxlc55@outlook.com
Classifier: Programming Language :: Python :: 3
Classifier: License :: OSI Approved :: MIT License
Classifier: Operating System :: OS Independent
License-File: LICENSE
